apropos.py
setup.py
apropos.egg-info/PKG-INFO
apropos.egg-info/SOURCES.txt
apropos.egg-info/dependency_links.txt
apropos.egg-info/top_level.txt