Metadata-Version: 1.0
Name: apropos
Version: 0.1.0
Summary: track the state of things
Home-page: UNKNOWN
Author: David Keijser
Author-email: keijser@gmail.com
License: MIT
Keywords: tracker
Platform: UNKNOWN
